lightchain/__init__.py
lightchain-0.0.1.dist-info/METADATA
lightchain-0.0.1.dist-info/WHEEL
lightchain-0.0.1.dist-info/top_level.txt
lightchain-0.0.1.dist-info/RECORD
