Metadata-Version: 2.1
Name: lightchain
Version: 0.0.1
Requires-Dist: openai
Requires-Dist: beautifulsoup4
Requires-Dist: requests
Requires-Dist: google-api-python-client
